{"cameraMode":{"drawMode":0,"name":"Shaded","section":"Shading Mode"},"sceneLighting":false,"audioPlay":false,"sceneViewState":{"m_AlwaysRefresh":false,"showFog":true,"showSkybox":false,"showFlares":true,"showImageEffects":true,"showParticleSystems":true,"showVisualEffectGraphs":true,"m_FxEnabled":true},"in2DMode":false,"pivot":{"x":-0.05330897867679596,"y":0.11589059233665467,"z":-0.0001047477126121521},"rotation":{"x":-0.011449305340647698,"y":0.9830740094184876,"z":-0.17158496379852296,"w":-0.06471673399209976},"size":0.3545339107513428,"orthographic":false}